LICENSE
README.md
setup.py
lib/waipy/__init__.py
lib/waipy/mainmodule.py
lib/waipy.egg-info/PKG-INFO
lib/waipy.egg-info/SOURCES.txt
lib/waipy.egg-info/dependency_links.txt
lib/waipy.egg-info/requires.txt
lib/waipy.egg-info/top_level.txt
lib/waipy/cwa/__init__.py
lib/waipy/cwa/cross_wavelet.py
lib/waipy/cwt/__init__.py
lib/waipy/cwt/lib_wavelet.py
lib/waipy/cwt/wavetest.py