Metadata-Version: 2.1
Name: waipy
Version: 0.1.51
Summary: Wavelet Analysis in Python
Home-page: https://bitbucket.org/mabel/waipy/overview
Author: Mabel Calim Costa
Author-email: mabelcalim@gmail.com
License: UNKNOWN
Platform: UNKNOWN
Classifier: License :: OSI Approved :: BSD License
Provides-Extra: all
Provides-Extra: jupyer
Provides-Extra: load_netcdf
